lumie/__init__.py
lumie/dimension/__init__.py
lumie/expression/__init__.py
lumie/free_z_module/__init__.py
lumie/quantity/__init__.py
lumie/scale/__init__.py
lumie/symbol/__init__.py
lumie/unit/__init__.py
lumie/unit_system/__init__.py
lumie-0.0.1.dist-info/licenses/LICENSE
lumie-0.0.1.dist-info/WHEEL
lumie-0.0.1.dist-info/METADATA
lumie-0.0.1.dist-info/RECORD
