Metadata-Version: 2.4
Name: lumie
Version: 0.0.1
Summary: Lightweight Units Made Intuitive & Easy
Keywords: units,dimensions,quantity,SI,measurement
Author: Ryuichi Suzuki
Requires-Python: >=3.10
Classifier: Development Status :: 2 - Pre-Alpha
Classifier: Intended Audience :: Science/Research
Classifier: License :: OSI Approved :: MIT License
Classifier: Programming Language :: Python :: 3
Classifier: Programming Language :: Python :: 3 :: Only
Classifier: Programming Language :: Python :: 3.10
Classifier: Programming Language :: Python :: 3.11
Classifier: Programming Language :: Python :: 3.12
Classifier: Programming Language :: Python :: 3.13
Classifier: Topic :: Scientific/Engineering
License-File: LICENSE
Project-URL: Homepage, https://github.com/RyuichiSuzuki101111/lumie
Project-URL: Issues, https://github.com/RyuichiSuzuki101111/lumie/issues
